win32/__init__.py
win32/_api.pyd
win32/_authorization.pyd
win32/_clipboard.pyd
win32/_com.pyd
win32/_console.pyd
win32/_credentials.pyd
win32/_cryptography.pyd
win32/_event.pyd
win32/_eventlog.pyd
win32/_file.pyd
win32/_help.pyd
win32/_inet.pyd
win32/_internet.pyd
win32/_job.pyd
win32/_kras.pyd
win32/_lz.pyd
win32/_mapi.pyd
win32/_net.pyd
win32/_pdh.pyd
win32/_perfmon.pyd
win32/_pipe.pyd
win32/_print.pyd
win32/_process.pyd
win32/_profile.pyd
win32/_propsys.pyd
win32/_ras.pyd
win32/_security.pyd
win32/_service.pyd
win32/_servicemanager.pyd
win32/_shell.pyd
win32/_sysloader.pyd
win32/_taskscheduler.pyd
win32/_timer.pyd
win32/_trace.pyd
win32/_transaction.pyd
win32/_ts.pyd
win32/_wnet.pyd
win32/adsi.pyd
win32/afxres.py
win32/bits.pyd
win32/commctrl.py
win32/compat.py
win32/constants.py
win32/dbi.py
win32/error.py
win32/exchange.pyd
win32/ifilter.pyd
win32/mmapfile.pyd
win32/mmsystem.py
win32/odbc.pyd
win32/rasutil.py
win32/rcparser.py
win32/regcheck.py
win32/regutil.py
win32/timezone.py
win32/types.pyd
win32/verstamp.py
win32/winioctlcon.py
win32/winnt.py
win32/api/__init__.py
win32/authorization/__init__.py
win32/clipboard/__init__.py
win32/com/__init__.py
win32/com/olectl.py
win32/com/universal.py
win32/com/util.py
win32/com/client/CLSIDToClass.py
win32/com/client/__init__.py
win32/com/client/build.py
win32/com/client/combrowse.py
win32/com/client/connect.py
win32/com/client/dynamic.py
win32/com/client/gencache.py
win32/com/client/genpy.py
win32/com/client/makepy.py
win32/com/client/selecttlb.py
win32/com/client/tlbrowse.py
win32/com/client/util.py
win32/com/gen_py/__init__.py
win32/com/makegw/__init__.py
win32/com/makegw/makegw.py
win32/com/makegw/makegwenum.py
win32/com/makegw/makegwparse.py
win32/com/server/__init__.py
win32/com/server/connect.py
win32/com/server/dispatcher.py
win32/com/server/exception.py
win32/com/server/factory.py
win32/com/server/localserver.py
win32core-221.35.dist-info/DESCRIPTION.rst
win32core-221.35.dist-info/METADATA
win32core-221.35.dist-info/RECORD
win32core-221.35.dist-info/WHEEL
win32core-221.35.dist-info/entry_points.txt
win32core-221.35.dist-info/metadata.json
win32core-221.35.dist-info/top_level.txt
