Metadata-Version: 2.0
Name: win32core
Version: 221.35
Summary: Python for Window Extensions
Home-page: http://sourceforge.net/projects/pywin32/
Author: Mark Hammond (et al)
Author-email: mhammond@users.sourceforge.net
License: PSF
Platform: UNKNOWN
